CommonTelegramUsers/__init__.py
CommonTelegramUsers/main.py
CommonTelegramUsers-0.2.7.dist-info/METADATA
CommonTelegramUsers-0.2.7.dist-info/WHEEL
CommonTelegramUsers-0.2.7.dist-info/top_level.txt
CommonTelegramUsers-0.2.7.dist-info/RECORD
