Metadata-Version: 2.1
Name: CommonTelegramUsers
Version: 0.2.7
Requires-Dist: pyrogram
Requires-Dist: tgcrypto
